mapkick/__init__.py
mapkick/django/__init__.py
mapkick/django/static/mapkick.bundle.js
mapkick/flask/__init__.py
mapkick/licenses/LICENSE-mapkick-bundle.txt
mapkick-0.2.0.dist-info/licenses/LICENSE.txt
mapkick-0.2.0.dist-info/METADATA
mapkick-0.2.0.dist-info/WHEEL
mapkick-0.2.0.dist-info/top_level.txt
mapkick-0.2.0.dist-info/RECORD
