Metadata-Version: 2.4
Name: mapkick
Version: 0.2.0
Summary: Create beautiful JavaScript maps with one line of Python
Author-email: Andrew Kane <andrew@ankane.org>
License: MIT
Project-URL: Homepage, https://github.com/ankane/mapkick.py
Requires-Python: >=3.9
License-File: LICENSE.txt
Dynamic: license-file
